README.md
setup.cfg
setup.py
models/__init__.py
roomai/RoomAIUtils.py
roomai/__init__.py
roomai.egg-info/PKG-INFO
roomai.egg-info/SOURCES.txt
roomai.egg-info/dependency_links.txt
roomai.egg-info/not-zip-safe
roomai.egg-info/top_level.txt
roomai/bridge/BridgeAction.py
roomai/bridge/BridgeEnv.py
roomai/bridge/BridgePersonState.py
roomai/bridge/BridgePrivateState.py
roomai/bridge/BridgePublicState.py
roomai/bridge/BridgeUtils.py
roomai/bridge/__init__.py
roomai/common/AbstractAction.py
roomai/common/AbstractActionChance.py
roomai/common/AbstractEnv.py
roomai/common/AbstractPersonState.py
roomai/common/AbstractPlayer.py
roomai/common/AbstractPlayerChance.py
roomai/common/AbstractPrivateState.py
roomai/common/AbstractPublicState.py
roomai/common/CommonUtils.py
roomai/common/Info.py
roomai/common/__init__.py
roomai/doudizhupoker/DouDiZhuPokerAction.py
roomai/doudizhupoker/DouDiZhuPokerEnv.py
roomai/doudizhupoker/DouDiZhuPokerHandCards.py
roomai/doudizhupoker/DouDiZhuPokerPersonState.py
roomai/doudizhupoker/DouDiZhuPokerPrivateState.py
roomai/doudizhupoker/DouDiZhuPokerPublicState.py
roomai/doudizhupoker/__init__.py
roomai/doudizhupoker/actions.py
roomai/doudizhupoker/patterns.py
roomai/fivecardstud/FiveCardStudAction.py
roomai/fivecardstud/FiveCardStudEnv.py
roomai/fivecardstud/FiveCardStudPersonState.py
roomai/fivecardstud/FiveCardStudPrivateState.py
roomai/fivecardstud/FiveCardStudPublicState.py
roomai/fivecardstud/FiveCardStudUtils.py
roomai/fivecardstud/__init__.py
roomai/kuhn/KuhnPokerAction.py
roomai/kuhn/KuhnPokerActionChance.py
roomai/kuhn/KuhnPokerEnv.py
roomai/kuhn/KuhnPokerPersonState.py
roomai/kuhn/KuhnPokerPlayer.py
roomai/kuhn/KuhnPokerPrivateState.py
roomai/kuhn/KuhnPokerPublicState.py
roomai/kuhn/__init__.py
roomai/sevenking/SevenKingAction.py
roomai/sevenking/SevenKingEnv.py
roomai/sevenking/SevenKingPersonState.py
roomai/sevenking/SevenKingPlayer.py
roomai/sevenking/SevenKingPrivateState.py
roomai/sevenking/SevenKingPublicState.py
roomai/sevenking/SevenKingUtils.py
roomai/sevenking/__init__.py
roomai/sevenking/play.py
roomai/texas/TexasHoldemAction.py
roomai/texas/TexasHoldemEnv.py
