Metadata-Version: 1.0
Name: roomai
Version: 0.1.16
Summary: A toolkit for developing and comparing imperfect information game bots
Home-page: https://github.com/roomai/RoomAI
Author: RoomAI Dev
Author-email: lili1987mail@gmail.com
License: MIT
Platform: UNKNOWN
